cdict/__init__.py
cdict/core.py
cdict/utils.py
cdict-2.1.4.dist-info/LICENSE
cdict-2.1.4.dist-info/METADATA
cdict-2.1.4.dist-info/WHEEL
cdict-2.1.4.dist-info/top_level.txt
cdict-2.1.4.dist-info/RECORD
